mondrianforest/__init__.py
mondrianforest/classifier.py
mondrianforest/forest.py
mondrianforest/node.py
mondrianforest/regressor.py
mondrianforest-0.0.2.dist-info/DESCRIPTION.rst
mondrianforest-0.0.2.dist-info/METADATA
mondrianforest-0.0.2.dist-info/RECORD
mondrianforest-0.0.2.dist-info/WHEEL
mondrianforest-0.0.2.dist-info/metadata.json
mondrianforest-0.0.2.dist-info/top_level.txt
