Metadata-Version: 2.0
Name: mondrianforest
Version: 0.0.2
Summary: UNKNOWN
Home-page: https://github.com/nel215/mondrianforest
Author: nel215
Author-email: otomo.yuhei@gmail.com
License: UNKNOWN
Keywords: machine learning
Platform: UNKNOWN
Classifier: Development Status :: 3 - Alpha
Classifier: Environment :: Console
Classifier: License :: OSI Approved :: MIT License
Classifier: Topic :: Scientific/Engineering :: Artificial Intelligence
Requires-Dist: numpy
